mcp_die_roller_server/__init__.py
mcp_die_roller_server/__main__.py
mcp_die_roller_server/main.py
mcp_die_roller_server-0.1.0.dist-info/METADATA
mcp_die_roller_server-0.1.0.dist-info/WHEEL
mcp_die_roller_server-0.1.0.dist-info/entry_points.txt
mcp_die_roller_server-0.1.0.dist-info/RECORD
