Metadata-Version: 2.4
Name: mcp-die-roller-server
Version: 0.1.0
Summary: Add your description here
Requires-Python: >=3.12
Requires-Dist: fastmcp
Requires-Dist: pydiceroll
